climacta_sdk/__init__.py
climacta_sdk/app.py
climacta_sdk-0.1.5.dist-info/METADATA
climacta_sdk-0.1.5.dist-info/WHEEL
climacta_sdk-0.1.5.dist-info/RECORD
