Metadata-Version: 2.1
Name: climacta-sdk
Version: 0.1.5
Summary: 
Author: Pedro
Author-email: pedrohenriquesoaress2016@gmail.com
Requires-Python: >=3.12,<4.0
Classifier: Programming Language :: Python :: 3
Classifier: Programming Language :: Python :: 3.12
Requires-Dist: datetime (>=5.5,<6.0)
Requires-Dist: openpyxl (>=3.1.5,<4.0.0)
Requires-Dist: pandas (>=2.2.2,<3.0.0)
Requires-Dist: requests (>=2.32.3,<3.0.0)
